quantum_starter_lab/__init__.py
quantum_starter_lab/api.py
quantum_starter_lab/cli.py
quantum_starter_lab/explain.py
quantum_starter_lab/plotting.py
quantum_starter_lab/results.py
quantum_starter_lab/demos/bell.py
quantum_starter_lab/demos/bv.py
quantum_starter_lab/demos/dj.py
quantum_starter_lab/demos/grover.py
quantum_starter_lab/demos/qft.py
quantum_starter_lab/demos/teleportation.py
quantum_starter_lab/ir/__init__.py
quantum_starter_lab/ir/ascii.py
quantum_starter_lab/ir/circuit.py
quantum_starter_lab/noise/__init__.py
quantum_starter_lab/noise/cirq_noise.py
quantum_starter_lab/noise/qiskit_noise.py
quantum_starter_lab/noise/spec.py
quantum_starter_lab/runners/__init__.py
quantum_starter_lab/runners/base.py
quantum_starter_lab/runners/cirq_runner.py
quantum_starter_lab/runners/qiskit_runner.py
quantum_starter_lab/utils/__init__.py
quantum_starter_lab/utils/bitstrings.py
quantum_starter_lab/utils/hist.py
quantum_starter_lab/utils/rng.py
quantum_starter_lab-0.1.6.dist-info/METADATA
quantum_starter_lab-0.1.6.dist-info/WHEEL
quantum_starter_lab-0.1.6.dist-info/entry_points.txt
quantum_starter_lab-0.1.6.dist-info/licenses/LICENSE
quantum_starter_lab-0.1.6.dist-info/RECORD
