Metadata-Version: 2.4
Name: quantum-starter-lab
Version: 0.1.6
Summary: A Python package for quantum computing demos, simulations, and NISQ research tools.
Project-URL: Repository, https://github.com/Pranava-Kumar/quantum-starter-lab
Project-URL: Documentation, https://pranava-kumar.github.io/quantum-starter-lab
Project-URL: Changelog, https://github.com/Pranava-Kumar/quantum-starter-lab/blob/main/RELEASE_NOTES.md
Author-email: Pranava Kumar <pranavakumar.it@gmail.com>
License: Apache-2.0
License-File: LICENSE
Keywords: cirq,education,nisq,qiskit,quantum algorithms,quantum computing,research,simulation
Classifier: Development Status :: 3 - Alpha
Classifier: Intended Audience :: Developers
Classifier: Intended Audience :: Education
Classifier: Intended Audience :: Science/Research
Classifier: License :: OSI Approved :: Apache Software License
Classifier: Operating System :: OS Independent
Classifier: Programming Language :: Python :: 3
Classifier: Programming Language :: Python :: 3.10
Classifier: Programming Language :: Python :: 3.11
Classifier: Programming Language :: Python :: 3.12
Classifier: Topic :: Education
Classifier: Topic :: Scientific/Engineering :: Physics
Requires-Python: >=3.10
Requires-Dist: cirq<2.0.0,>=1.3.0
Requires-Dist: matplotlib<4.0.0,>=3.8.0
Requires-Dist: numpy<2.0.0,>=1.26.0
Requires-Dist: pyqt6>=6.9.1
Requires-Dist: qiskit-aer<1.0.0,>=0.14.0
Requires-Dist: qiskit<2.0.0,>=1.0.0
